pyreleaser_io/__init__.py
pyreleaser_io/cli.py
pyreleaser_io/create.py
pyreleaser_io/github.py
pyreleaser_io/template.py
pyreleaser_io/util.py
pyreleaser_io/res/test.x
pyreleaser_io/res/templates/MANIFEST.in.jinja2
pyreleaser_io/res/templates/README.md.jinja2
pyreleaser_io/res/templates/setup.py.jinja2
pyreleaser_io/vcs/__init__.py
pyreleaser_io/vcs/github.py
pyreleaser_io/vcs/missing.py
pyreleaser_io-0.0.3.dist-info/METADATA
pyreleaser_io-0.0.3.dist-info/WHEEL
pyreleaser_io-0.0.3.dist-info/entry_points.txt
pyreleaser_io-0.0.3.dist-info/top_level.txt
pyreleaser_io-0.0.3.dist-info/RECORD
