Metadata-Version: 2.1
Name: pyreleaser-io
Version: 0.0.3
Summary: create, test, publish your python projects!
Home-page: https://github.com/geoffwilliams/pyreleaser
Author: Geoff Williams
Author-email: geoff@declarativesystems.com
License: UNKNOWN
Platform: UNKNOWN
Classifier: Development Status :: 1 - Planning
Classifier: Programming Language :: Python :: 3
Classifier: License :: OSI Approved :: Apache Software License
Classifier: Operating System :: OS Independent
Requires-Python: >=3.6
